{
    "concurrent-1757546076671@example.com:login_code": {
        "attempts": [
            1757546077,
            1757546078,
            1757546079
        ],
        "blocked_until": 1757547880
    },
    "test0@example.com:signup_code": {
        "attempts": [
            1757546088
        ],
        "blocked_until": 0
    },
    "test1@example.com:signup_code": {
        "attempts": [
            1757546088
        ],
        "blocked_until": 0
    },
    "test2@example.com:signup_code": {
        "attempts": [
            1757546088
        ],
        "blocked_until": 0
    },
    "test3@example.com:signup_code": {
        "attempts": [
            1757546088
        ],
        "blocked_until": 0
    },
    "test4@example.com:signup_code": {
        "attempts": [
            1757546089
        ],
        "blocked_until": 0
    },
    "test5@example.com:signup_code": {
        "attempts": [
            1757546089
        ],
        "blocked_until": 0
    },
    "test6@example.com:signup_code": {
        "attempts": [
            1757546089
        ],
        "blocked_until": 0
    },
    "test7@example.com:signup_code": {
        "attempts": [
            1757546089
        ],
        "blocked_until": 0
    },
    "test8@example.com:signup_code": {
        "attempts": [
            1757546089
        ],
        "blocked_until": 0
    },
    "test9@example.com:signup_code": {
        "attempts": [
            1757546089
        ],
        "blocked_until": 0
    },
    "test0@example.com:login_code": {
        "attempts": [
            1757546089
        ],
        "blocked_until": 0
    },
    "test1@example.com:login_code": {
        "attempts": [
            1757546090
        ],
        "blocked_until": 0
    },
    "test2@example.com:login_code": {
        "attempts": [
            1757546091
        ],
        "blocked_until": 0
    },
    "test3@example.com:login_code": {
        "attempts": [
            1757546092
        ],
        "blocked_until": 0
    },
    "test4@example.com:login_code": {
        "attempts": [
            1757546093
        ],
        "blocked_until": 0
    },
    "test5@example.com:login_code": {
        "attempts": [
            1757546093
        ],
        "blocked_until": 0
    },
    "test6@example.com:login_code": {
        "attempts": [
            1757546094
        ],
        "blocked_until": 0
    },
    "test7@example.com:login_code": {
        "attempts": [
            1757546095
        ],
        "blocked_until": 0
    },
    "test8@example.com:login_code": {
        "attempts": [
            1757546096
        ],
        "blocked_until": 0
    }
}